otio_mlt_adapter/__init__.py
otio_mlt_adapter/plugin_manifest.json
otio_mlt_adapter/adapters/__init__.py
otio_mlt_adapter/adapters/mlt_xml.py
otio_mlt_adapter-0.3.0.dist-info/LICENSE.txt
otio_mlt_adapter-0.3.0.dist-info/METADATA
otio_mlt_adapter-0.3.0.dist-info/WHEEL
otio_mlt_adapter-0.3.0.dist-info/entry_points.txt
otio_mlt_adapter-0.3.0.dist-info/top_level.txt
otio_mlt_adapter-0.3.0.dist-info/RECORD
